{
	"@type":"Cube",
	"Name":"ST_PL_YTD",
	"Dimensions":
	[
		{
			"@id":"Dimensions('Activity')"
		},
		{
			"@id":"Dimensions('Currency')"
		},
		{
			"@id":"Dimensions('Gaap')"
		},
		{
			"@id":"Dimensions('Legal_Organization')"
		},
		{
			"@id":"Dimensions('Management_Organization')"
		},
		{
			"@id":"Dimensions('Period_YTD')"
		},
		{
			"@id":"Dimensions('Phase')"
		},
		{
			"@id":"Dimensions('Indicator')"
		}
	],
	"ViewStorageMaxMemory":100000,
	"ViewStorageMinTime":1,
	"Views@Code.links":
	[
		"ST_PL_YTD.views/ST_PL_YTD_Vue.json",
		"ST_PL_YTD.views/2024-01-Input_ST_PL_YTD.json",
		"ST_PL_YTD.views/2024-01-Input_ST_PL_YTD_Asymetrique.json",
		"ST_PL_YTD.views/Save Data  _ WEMR Input - Vue Test.json",
		"ST_PL_YTD.views/WEMR Input - Vue Test - croisement fin - Save Data.json",
		"ST_PL_YTD.views/WEMR Input - Vue Test - croisement fin - Save Data VF MBA.json"
	]
}