{
	"@type":"Subset",
	"Name":"F_year_2022-2029",
	"Elements":
	[
		{
			"@id":"Dimensions('Period')/Hierarchies('Period')/Elements('F_year_2022')"
		},
		{
			"@id":"Dimensions('Period')/Hierarchies('Period')/Elements('F_year_2023')"
		},
		{
			"@id":"Dimensions('Period')/Hierarchies('Period')/Elements('F_year_2024')"
		},
		{
			"@id":"Dimensions('Period')/Hierarchies('Period')/Elements('F_year_2025')"
		},
		{
			"@id":"Dimensions('Period')/Hierarchies('Period')/Elements('F_year_2026')"
		},
		{
			"@id":"Dimensions('Period')/Hierarchies('Period')/Elements('F_year_2027')"
		},
		{
			"@id":"Dimensions('Period')/Hierarchies('Period')/Elements('F_year_2028')"
		},
		{
			"@id":"Dimensions('Period')/Hierarchies('Period')/Elements('F_year_2029')"
		}
	]
}