{
	"@type":"NativeView",
	"Name":"Check Comments",
	"Columns":[],
	"Rows":
	[
		{
			"Subset":
			{
				"Hierarchy":
				{
					"@id":"Dimensions('Gaap')/Hierarchies('Gaap')"
				},
				"Elements":
				[
					{
						"@id":"Dimensions('Gaap')/Hierarchies('Gaap')/Elements('Total_conso')"
					},
					{
						"@id":"Dimensions('Gaap')/Hierarchies('Gaap')/Elements('Total_conso_wo_opt_dis')"
					},
					{
						"@id":"Dimensions('Gaap')/Hierarchies('Gaap')/Elements('IFRS_restated')"
					},
					{
						"@id":"Dimensions('Gaap')/Hierarchies('Gaap')/Elements('Local_Gaap')"
					},
					{
						"@id":"Dimensions('Gaap')/Hierarchies('Gaap')/Elements('Local_Gaap_Mgmt_tool')"
					}
				]
			}
		},
		{
			"Subset":
			{
				"Hierarchy":
				{
					"@id":"Dimensions('Integration_Rate')/Hierarchies('Integration_Rate')"
				},
				"Elements":
				[
					{
						"@id":"Dimensions('Integration_Rate')/Hierarchies('Integration_Rate')/Elements('NO_APP')"
					},
					{
						"@id":"Dimensions('Integration_Rate')/Hierarchies('Integration_Rate')/Elements('APP')"
					}
				]
			}
		},
		{
			"Subset":
			{
				"Hierarchy":
				{
					"@id":"Dimensions('ApplicationSheet')/Hierarchies('ApplicationSheet')"
				},
				"Elements":
				[
					{
						"@id":"Dimensions('ApplicationSheet')/Hierarchies('ApplicationSheet')/Elements('PL_aggregated')"
					}
				]
			}
		},
		{
			"Subset":
			{
				"Hierarchy":
				{
					"@id":"Dimensions('Legal_Organization')/Hierarchies('Legal_Organization')"
				},
				"Elements":
				[
					{
						"@id":"Dimensions('Legal_Organization')/Hierarchies('Legal_Organization')/Elements('GER')"
					},
					{
						"@id":"Dimensions('Legal_Organization')/Hierarchies('Legal_Organization')/Elements('NETH')"
					},
					{
						"@id":"Dimensions('Legal_Organization')/Hierarchies('Legal_Organization')/Elements('USA')"
					},
					{
						"@id":"Dimensions('Legal_Organization')/Hierarchies('Legal_Organization')/Elements('FR')"
					},
					{
						"@id":"Dimensions('Legal_Organization')/Hierarchies('Legal_Organization')/Elements('VTD_corp')"
					}
				]
			}
		},
		{
			"Subset":
			{
				"Hierarchy":
				{
					"@id":"Dimensions('Management_Organization')/Hierarchies('Management_Organization')"
				},
				"Elements":
				[
					{
						"@id":"Dimensions('Management_Organization')/Hierarchies('Management_Organization')/Elements('VTD_corp')"
					},
					{
						"@id":"Dimensions('Management_Organization')/Hierarchies('Management_Organization')/Elements('FR')"
					},
					{
						"@id":"Dimensions('Management_Organization')/Hierarchies('Management_Organization')/Elements('GER')"
					},
					{
						"@id":"Dimensions('Management_Organization')/Hierarchies('Management_Organization')/Elements('NETH')"
					},
					{
						"@id":"Dimensions('Management_Organization')/Hierarchies('Management_Organization')/Elements('USA')"
					}
				]
			}
		},
		{
			"Subset":
			{
				"Hierarchy":
				{
					"@id":"Dimensions('Comment')/Hierarchies('Comment')"
				},
				"Expression":"TM1SubsetAll([Comment])"
			}
		},
		{
			"Subset":
			{
				"Hierarchy":
				{
					"@id":"Dimensions('Period')/Hierarchies('Period')"
				},
				"Elements":[]
			}
		}
	],
	"Titles":
	[
		{
			"Subset":
			{
				"Hierarchy":
				{
					"@id":"Dimensions('Activity')/Hierarchies('Activity')"
				},
				"Elements":
				[
					{
						"@id":"Dimensions('Activity')/Hierarchies('Activity')/Elements('Tot_act')"
					},
					{
						"@id":"Dimensions('Activity')/Hierarchies('Activity')/Elements('UR')"
					},
					{
						"@id":"Dimensions('Activity')/Hierarchies('Activity')/Elements('SU')"
					},
					{
						"@id":"Dimensions('Activity')/Hierarchies('Activity')/Elements('SO')"
					},
					{
						"@id":"Dimensions('Activity')/Hierarchies('Activity')/Elements('RC')"
					},
					{
						"@id":"Dimensions('Activity')/Hierarchies('Activity')/Elements('HRAIL')"
					},
					{
						"@id":"Dimensions('Activity')/Hierarchies('Activity')/Elements('NIC')"
					},
					{
						"@id":"Dimensions('Activity')/Hierarchies('Activity')/Elements('FE')"
					},
					{
						"@id":"Dimensions('Activity')/Hierarchies('Activity')/Elements('CO')"
					},
					{
						"@id":"Dimensions('Activity')/Hierarchies('Activity')/Elements('AT')"
					},
					{
						"@id":"Dimensions('Activity')/Hierarchies('Activity')/Elements('OS')"
					},
					{
						"@id":"Dimensions('Activity')/Hierarchies('Activity')/Elements('HO')"
					},
					{
						"@id":"Dimensions('Activity')/Hierarchies('Activity')/Elements('NA')"
					},
					{
						"@id":"Dimensions('Activity')/Hierarchies('Activity')/Elements('Reject_Data')"
					}
				]
			},
			"Selected":
			{
				"@id":"Dimensions('Activity')/Hierarchies('Activity')/Elements('Tot_act')"
			}
		}
	],
	"SuppressEmptyColumns":false,
	"SuppressEmptyRows":true,
	"FormatString":"0.#########"
}