{
	"@type":"Process",
	"Name":"DL_TC_CONTRACT_ECO_MO_TYP_CLI_STEP2",
	"HasSecurityAccess":false,
	"Code@Code.link":"DL_TC_CONTRACT_ECO_MO_TYP_CLI_STEP2.ti",
	"UIData":"CubeAction=1511\fDataAction=1503\fCubeLogChanges=0\f",
	"VariablesUIData":
	[
		"VarType=32\fColType=827\f",
		"VarType=32\fColType=827\f",
		"VarType=32\fColType=827\f",
		"VarType=32\fColType=827\f",
		"VarType=32\fColType=827\f"
	],
	"DataSource":
	{
		"Type":"TM1CubeView",
		"dataSourceNameForClient":"TC_CONTRACT_ECO_MO_TYP_CLI",
		"dataSourceNameForServer":"TC_CONTRACT_ECO_MO_TYP_CLI",
		"view":"Par défaut"
	},
	"Parameters":
	[
		{
			"Name":"pContract",
			"Prompt":"",
			"Value":"SW_3510",
			"Type":"String"
		},
		{
			"Name":"pActivity",
			"Prompt":"",
			"Value":"UR_LR",
			"Type":"String"
		}
	],
	"Variables":
	[
		{
			"Name":"V_Legal_Organization",
			"Type":"String",
			"Position":2,
			"StartByte":0,
			"EndByte":0
		},
		{
			"Name":"V_Management_Organization",
			"Type":"String",
			"Position":3,
			"StartByte":0,
			"EndByte":0
		},
		{
			"Name":"V_Activity",
			"Type":"String",
			"Position":1,
			"StartByte":0,
			"EndByte":0
		},
		{
			"Name":"z_Str_Var",
			"Type":"String",
			"Position":4,
			"StartByte":0,
			"EndByte":0
		},
		{
			"Name":"V_Value",
			"Type":"String",
			"Position":5,
			"StartByte":0,
			"EndByte":0
		}
	]
}