{
	"@type":"Process",
	"Name":"z_Admin_Users_Groups_Securities",
	"HasSecurityAccess":true,
	"Code@Code.link":"z_Admin_Users_Groups_Securities.ti",
	"UIData":"CubeAction=1511\fDataAction=1503\fCubeLogChanges=0\f",
	"VariablesUIData":
	[
		"VarType=32\fColType=827\f",
		"VarType=32\fColType=827\f",
		"VarType=32\fColType=827\f",
		"VarType=32\fColType=827\f",
		"VarType=32\fColType=827\f",
		"VarType=32\fColType=827\f",
		"VarType=32\fColType=827\f",
		"VarType=32\fColType=827\f",
		"VarType=32\fColType=827\f",
		"VarType=33\fColType=827\f",
		"VarType=32\fColType=827\f",
		"VarType=32\fColType=827\f",
		"VarType=32\fColType=827\f",
		"VarType=32\fColType=827\f",
		"VarType=32\fColType=827\f",
		"VarType=32\fColType=827\f",
		"VarType=32\fColType=827\f",
		"VarType=32\fColType=827\f",
		"VarType=32\fColType=827\f",
		"VarType=32\fColType=827\f",
		"VarType=32\fColType=827\f",
		"VarType=32\fColType=827\f",
		"VarType=32\fColType=827\f",
		"VarType=32\fColType=827\f",
		"VarType=32\fColType=827\f",
		"VarType=32\fColType=827\f",
		"VarType=32\fColType=827\f",
		"VarType=32\fColType=827\f",
		"VarType=32\fColType=827\f",
		"VarType=32\fColType=827\f",
		"VarType=32\fColType=827\f",
		"VarType=32\fColType=827\f",
		"VarType=32\fColType=827\f",
		"VarType=32\fColType=827\f",
		"VarType=32\fColType=827\f",
		"VarType=32\fColType=827\f",
		"IgnoredInputVarName=Comment\fVarType=33\fColType=1165\f"
	],
	"DataSource":
	{
		"Type":"ASCII",
		"asciiDecimalSeparator":",",
		"asciiDelimiterChar":";",
		"asciiDelimiterType":"Character",
		"asciiHeaderRecords":3,
		"asciiQuoteCharacter":"\"",
		"asciiThousandSeparator":" ",
		"dataSourceNameForClient":"\\\\tfr-ap019298\\TM1Data\\Tango_core_model_bck\\Input\\Structure\\Tango_Users_Groups_Securities.csv",
		"dataSourceNameForServer":"Defined into prolog tab"
	},
	"Parameters":[],
	"Variables":
	[
		{
			"Name":"vLastName",
			"Type":"String",
			"Position":1,
			"StartByte":0,
			"EndByte":0
		},
		{
			"Name":"vFirstName",
			"Type":"String",
			"Position":2,
			"StartByte":0,
			"EndByte":0
		},
		{
			"Name":"vLogin",
			"Type":"String",
			"Position":3,
			"StartByte":0,
			"EndByte":0
		},
		{
			"Name":"vLanguage",
			"Type":"String",
			"Position":4,
			"StartByte":0,
			"EndByte":0
		},
		{
			"Name":"veMail",
			"Type":"String",
			"Position":5,
			"StartByte":0,
			"EndByte":0
		},
		{
			"Name":"vLegal_Organization",
			"Type":"String",
			"Position":6,
			"StartByte":0,
			"EndByte":0
		},
		{
			"Name":"vManagement_Organization",
			"Type":"String",
			"Position":7,
			"StartByte":0,
			"EndByte":0
		},
		{
			"Name":"vLegal_Organization_corp",
			"Type":"String",
			"Position":8,
			"StartByte":0,
			"EndByte":0
		},
		{
			"Name":"vManagement_Organization_corp",
			"Type":"String",
			"Position":9,
			"StartByte":0,
			"EndByte":0
		},
		{
			"Name":"LTP_Corp_Security",
			"Type":"Numeric",
			"Position":10,
			"StartByte":0,
			"EndByte":0
		},
		{
			"Name":"Group_1",
			"Type":"String",
			"Position":11,
			"StartByte":0,
			"EndByte":0
		},
		{
			"Name":"Group_2",
			"Type":"String",
			"Position":12,
			"StartByte":0,
			"EndByte":0
		},
		{
			"Name":"Group_3",
			"Type":"String",
			"Position":13,
			"StartByte":0,
			"EndByte":0
		},
		{
			"Name":"Group_4",
			"Type":"String",
			"Position":14,
			"StartByte":0,
			"EndByte":0
		},
		{
			"Name":"Group_5",
			"Type":"String",
			"Position":15,
			"StartByte":0,
			"EndByte":0
		},
		{
			"Name":"Group_6",
			"Type":"String",
			"Position":16,
			"StartByte":0,
			"EndByte":0
		},
		{
			"Name":"Group_7",
			"Type":"String",
			"Position":17,
			"StartByte":0,
			"EndByte":0
		},
		{
			"Name":"Group_8",
			"Type":"String",
			"Position":18,
			"StartByte":0,
			"EndByte":0
		},
		{
			"Name":"Group_9",
			"Type":"String",
			"Position":19,
			"StartByte":0,
			"EndByte":0
		},
		{
			"Name":"Group_10",
			"Type":"String",
			"Position":20,
			"StartByte":0,
			"EndByte":0
		},
		{
			"Name":"Group_11",
			"Type":"String",
			"Position":21,
			"StartByte":0,
			"EndByte":0
		},
		{
			"Name":"Group_12",
			"Type":"String",
			"Position":22,
			"StartByte":0,
			"EndByte":0
		},
		{
			"Name":"Group_13",
			"Type":"String",
			"Position":23,
			"StartByte":0,
			"EndByte":0
		},
		{
			"Name":"Group_14",
			"Type":"String",
			"Position":24,
			"StartByte":0,
			"EndByte":0
		},
		{
			"Name":"Group_15",
			"Type":"String",
			"Position":25,
			"StartByte":0,
			"EndByte":0
		},
		{
			"Name":"Group_16",
			"Type":"String",
			"Position":26,
			"StartByte":0,
			"EndByte":0
		},
		{
			"Name":"Group_17",
			"Type":"String",
			"Position":27,
			"StartByte":0,
			"EndByte":0
		},
		{
			"Name":"Group_18",
			"Type":"String",
			"Position":28,
			"StartByte":0,
			"EndByte":0
		},
		{
			"Name":"Group_19",
			"Type":"String",
			"Position":29,
			"StartByte":0,
			"EndByte":0
		},
		{
			"Name":"Group_20",
			"Type":"String",
			"Position":30,
			"StartByte":0,
			"EndByte":0
		},
		{
			"Name":"vPoste",
			"Type":"String",
			"Position":31,
			"StartByte":0,
			"EndByte":0
		},
		{
			"Name":"vZone",
			"Type":"String",
			"Position":32,
			"StartByte":0,
			"EndByte":0
		},
		{
			"Name":"vZoneDetail",
			"Type":"String",
			"Position":33,
			"StartByte":0,
			"EndByte":0
		},
		{
			"Name":"V34",
			"Type":"String",
			"Position":34,
			"StartByte":0,
			"EndByte":0
		},
		{
			"Name":"Creation",
			"Type":"String",
			"Position":35,
			"StartByte":0,
			"EndByte":0
		},
		{
			"Name":"Modif",
			"Type":"String",
			"Position":36,
			"StartByte":0,
			"EndByte":0
		}
	]
}