{
	"@type":"Chore",
	"Name":"DL_GIE_Data_ACTUAL",
	"StartTime":"2016-02-19T15:50:51Z",
	"DSTSensitive":false,
	"Active":false,
	"ExecutionMode":"SingleCommit",
	"Frequency":"P1DT00H00M00S",
	"Tasks":
	[
		{
			"Step":0,
			"Parameters":
			[
				{
					"Name":"PS_PERIOD",
					"Value":"Param"
				}
			],
			"Process":
			{
				"@id":"Processes('DL_ST_GIE_Transdev_Formation_Actual_P&L')"
			}
		},
		{
			"Step":1,
			"Parameters":
			[
				{
					"Name":"PS_Period",
					"Value":"Param"
				}
			],
			"Process":
			{
				"@id":"Processes('DL_RP_GIE_TD_Formation_ST_GIE_TD_Formation')"
			}
		}
	]
}